djangocms_faq/__init__.py
djangocms_faq/admin.py
djangocms_faq/apps.py
djangocms_faq/cms_plugins.py
djangocms_faq/models.py
djangocms_faq/settings.py
djangocms_faq/urls.py
djangocms_faq/utils.py
djangocms_faq/views.py
djangocms_faq/locale/fr/LC_MESSAGES/django.mo
djangocms_faq/locale/fr/LC_MESSAGES/django.po
djangocms_faq/migrations/0001_initial.py
djangocms_faq/migrations/0002_auto_20210531_1650.py
djangocms_faq/migrations/0003_auto_20210825_1012.py
djangocms_faq/migrations/__init__.py
djangocms_faq/templates/admin/change_form_help_text.html
djangocms_faq/templates/faq/faq_plugin.html
djangocms_faq/templates/faq/faq_question.html
djangocms_faq/templates/faq/faq_search.html
djangocms_faq-1.5.2.dist-info/AUTHORS.md
djangocms_faq-1.5.2.dist-info/LICENSE
djangocms_faq-1.5.2.dist-info/METADATA
djangocms_faq-1.5.2.dist-info/WHEEL
djangocms_faq-1.5.2.dist-info/top_level.txt
djangocms_faq-1.5.2.dist-info/RECORD
