Metadata-Version: 2.1
Name: djangocms-faq
Version: 1.5.2
Summary: DjangoCMS FAQ let you create FAQ plugins that contains other plugins and provide an API to get questions/answers from keywords!
Home-page: https://gitlab.com/kapt/open-source/djangocms-faq
Author: Dev Kapt
Author-email: dev@kapt.mobi
Classifier: Environment :: Web Environment
Classifier: Framework :: Django
Classifier: Framework :: Django :: 2.2
Classifier: Framework :: Django :: 3.1
Classifier: Intended Audience :: Developers
Classifier: License :: OSI Approved :: GNU General Public License v3 (GPLv3)
Classifier: Programming Language :: Python
Classifier: Programming Language :: Python :: 3
Classifier: Topic :: Internet :: WWW/HTTP
Classifier: Topic :: Internet :: WWW/HTTP :: Dynamic Content
License-File: LICENSE
License-File: AUTHORS.md
Requires-Dist: django-cms
Provides-Extra: fuzzy_search
Requires-Dist: thefuzz ; extra == 'fuzzy_search'
